inspiring_quotes/__init__.py
inspiring_quotes/quotes.py
inspiring_quotes/quotes_list.json
inspiring_quotes-1.5.1.dist-info/LICENSE
inspiring_quotes-1.5.1.dist-info/METADATA
inspiring_quotes-1.5.1.dist-info/WHEEL
inspiring_quotes-1.5.1.dist-info/top_level.txt
inspiring_quotes-1.5.1.dist-info/RECORD
