Metadata-Version: 2.1
Name: inspiring_quotes
Version: 1.5.1
Summary: A simple Python package for retrieving random inspirational quotes.
Home-page: https://github.com/cyberdeeb/inspiring-quotes
Author: cyberdeeb
Author-email: abrahamdeeb@gmail.com
Keywords: quotes inspirational motivational wisdom positivity self-improvement
Classifier: Intended Audience :: Developers
Classifier: License :: OSI Approved :: MIT License
Classifier: Programming Language :: Python :: 3.6
Classifier: Programming Language :: Python :: 3.7
Classifier: Programming Language :: Python :: 3.8
Classifier: Programming Language :: Python :: 3.9
Requires-Python: >=3.6
License-File: LICENSE
